[
   {
      "meno": "Janka",
      "priezvisko": "Mrkvičková",
      "pohlavie":"zena",
      "praca": "ziak",
      "oneskorenie": "1500",
      "surodenci": "2",
      "vek": "15",
      "hmotnost": "55",
      "vztah": "ano",
      "deti": "nie",
      "byvanie": "byt",
      "uspory": "nie"
   },
   {
      "meno":"Martin",
      "priezvisko":"Mrkvička",
      "pohlavie":"muz",
      "praca": "ucitel",
      "oneskorenie": "1000",
      "surodenci": "0",
      "vek": "48",
      "hmotnost": "90",
      "vztah": "nie",
      "deti": "ano",
      "byvanie": "dom",
      "uspory": "nie"
   },
   {
      "meno":"Mária",
      "priezvisko":"Kôstková",
      "pohlavie":"zena",
      "praca": "ucitel",
      "oneskorenie": "2500",
      "surodenci": "0",
      "vek": "53",
      "hmotnost": "75",
      "vztah": "nie",
      "deti": "ano",
      "byvanie": "dom",
      "uspory": "ano"
   },
   {
      "meno":"Tomáš",
      "priezvisko":"Tekvica",
      "pohlavie":"muz",
      "praca": "ucitel",
      "oneskorenie": "4500",
      "surodenci": "1",
      "vek": "38",
      "hmotnost": "95",
      "vztah": "ano",
      "deti": "nie",
      "byvanie": "dom",
      "uspory": "ano"
   },
   {
      "meno":"Ján",
      "priezvisko":"Tekvica",
      "pohlavie":"muz",
      "praca": "ziak",
      "oneskorenie": "3000",
      "surodenci": "1",
      "vek": "18",
      "hmotnost": "66",
      "vztah": "nie",
      "deti": "ano",
      "byvanie": "dom",
      "uspory": "nie"
   },
   {
      "meno":"Renáta",
      "priezvisko":"Kôstková",
      "pohlavie":"zena",
      "praca": "ziak",
      "oneskorenie": "4000",
      "surodenci": "0",
      "vek": "18",
      "hmotnost": "50",
      "vztah": "nie",
      "deti": "ano",
      "byvanie": "byt",
      "uspory": "ano"
   },
   {
      "meno":"Michal",
      "priezvisko":"Tekvica",
      "pohlavie":"muz",
      "praca": "ucitel",
      "oneskorenie": "3500",
      "surodenci": "0",
      "vek": "42",
      "hmotnost": "79",
      "vztah": "ano",
      "deti": "nie",
      "byvanie": "byt",
      "uspory": "ano"
   },
   {
      "meno":"Tomáš",
      "priezvisko":"Mrkvička",
      "pohlavie":"muz",
      "praca": "ziak",
      "oneskorenie": "2000",
      "surodenci": "2",
      "vek": "16",
      "hmotnost": "83",
      "vztah": "ano",
      "deti": "nie",
      "byvanie": "byt",
      "uspory": "ano"
   },
   {
      "meno":"Lucia",
      "priezvisko":"Tekvicová",
      "pohlavie":"zena",
      "praca": "ziak",
      "oneskorenie": "2500",
      "surodenci": "1",
      "vek": "18",
      "hmotnost": "60",
      "vztah": "ano",
      "deti": "nie",
      "byvanie": "dom",
      "uspory": "nie"
   },
   {
      "meno":"Terézia",
      "priezvisko":"Mrkvičková",
      "pohlavie":"zena",
      "praca": "ucitel",
      "oneskorenie": "3000",
      "surodenci": "0",
      "vek": "35",
      "hmotnost": "70",
      "vztah": "nie",
      "deti": "ano",
      "byvanie": "byt",
      "uspory": "nie"
   },
   {
      "meno":"Eva",
      "priezvisko":"Tekvicová",
      "pohlavie":"zena",
      "praca": "ucitel",
      "oneskorenie": "2800",
      "surodenci": "1",
      "vek": "43",
      "hmotnost": "78",
      "vztah": "ano",
      "deti": "nie",
      "byvanie": "dom",
      "uspory": "nie"
   },
   {
      "meno":"Ján",
      "priezvisko":"Kôstka",
      "pohlavie":"muz",
      "praca": "žiak",
      "oneskorenie": "3500",
      "surodenci": "2",
      "vek": "17",
      "hmotnost": "65",
      "vztah": "nie",
      "deti": "ano",
      "byvanie": "byt",
      "uspory": "nie"
   },
   {
      "meno":"Peter",
      "priezvisko":"Mrkvička",
      "pohlavie":"muz",
      "praca": "ucitel",
      "oneskorenie": "2500",
      "surodenci": "1",
      "vek": "54",
      "hmotnost": "90",
      "vztah": "nie",
      "deti": "ano",
      "byvanie": "byt",
      "uspory": "nie"
   },
   {
      "meno":"Eva",
      "priezvisko":"Černá",
      "pohlavie":"zena",
      "praca": "ucitel",
      "oneskorenie": "3000",
      "surodenci": "0",
      "vek": "45",
      "hmotnost": "60",
      "vztah": "ano",
      "deti": "nie",
      "byvanie": "byt",
      "uspory": "ano"
   },
   {
      "meno":"Mária",
      "priezvisko":"Severská",
      "pohlavie":"zena",
      "praca": "žiak",
      "oneskorenie": "2800",
      "surodenci": "1",
      "vek": "19",
      "hmotnost": "58",
      "vztah": "nie",
      "deti": "ano",
      "byvanie": "dom",
      "uspory": "ano"
   },
   {
      "meno":"Tomáš",
      "priezvisko":"Fiala",
      "pohlavie":"muz",
      "praca": "žiak",
      "oneskorenie": "3500",
      "surodenci": "2",
      "vek": "18",
      "hmotnost": "65",
      "vztah": "ano",
      "deti": "nie",
      "byvanie": "dom",
      "uspory": "ano"
   }
]
